birthday/__init__.py
birthday/__main__.py
bday_song-1.0.1.dist-info/METADATA
bday_song-1.0.1.dist-info/WHEEL
bday_song-1.0.1.dist-info/entry_points.txt
bday_song-1.0.1.dist-info/top_level.txt
bday_song-1.0.1.dist-info/RECORD
